[
    {
        "date": "2026-06-30",
        "transactions": [
            {
                "type": "gider",
                "category": "alisveris",
                "title": "Araç Bagaj Havuzu",
                "amount": 467.46
            },
             {
                "type": "gider",
                "category": "taksit",
                "title": "trendyol son taksit",
                "amount": 708.34
            },
             {
                "type": "gider",
                "category": "taksit",
                "title": "tatil 4.taksit",
                "amount": 6500
            },
             {
                "type": "gider",
                "category": "taksit",
                "title": "tatil son taksit",
                "amount": 19.666
            },
            {
                "type": "gider",
                "category": "taksit",
                "title": "trendyol son taksit",
                "amount": 1566.60
            },
             {
                "type": "gider",
                "category": "taksit",
                "title": "hava temizleyici son taksit",
                "amount": 6900
            },
             {
                "type": "gider",
                "category": "taksit",
                "title": "trendyol son taksit",
                "amount": 2227.50
            },
             {
                "type": "gider",
                "category": "yardim",
                "title": "annemler",
                "amount": 35.000
            },
            {
                "type": "gider",
                "category": "saglik",
                "title": "kedi",
                "amount": 15.000
            },
             {
                "type": "gider",
                "category": "borc",
                "title": "kart ödemesi",
                "amount": 63.460
            },
             {
                "type": "gider",
                "category": "alisveris",
                "title": "trendyol",
                "amount": 75
            },
             {
                "type": "gider",
                "category": "alisveris",
                "title": "hepsiburada",
                "amount": 554
            },
             {
                "type": "gider",
                "category": "alisveris",
                "title": "trendyol",
                "amount": 597
            },
             {
                "type": "gider",
                "category": "alisveris",
                "title": "trendyol",
                "amount": 509
            },
            {
                "type": "gider",
                "category": "alisveris",
                "title": "trendyol",
                "amount": 260
            },
            {
                "type": "gider",
                "category": "alisveris",
                "title": "trendyol",
                "amount": 967.41
            },
             {
                "type": "gelir",
                "category": "bakiye",
                "title": "bakiye",
                "amount": 145000
            },
            {
                "type": "gider",
                "category": "alisveris",
                "title": "trendyol",
                "amount": 467.46
            }
            
        ]
    },
    {
        "date": "2026-07-02",
        "transactions": [
            {
                "type": "gider",
                "category": "alisveris",
                "title": "trendyol",
                "amount": 313.75
            },
            {
                "type": "gider",
                "category": "alisveris",
                "title": "lcw",
                "amount": 899.99
            },
            {
                "type": "gider",
                "category": "yemek",
                "title": "mado",
                "amount": 150
            }
        ]
    },
    {
        "date": "2026-07-03",
        "transactions": [
            {
                "type": "gider",
                "category": "taksit",
                "title": "decathlon ilk taksit",
                "amount": 565.30
            },
             {
                "type": "gider",
                "category": "saglik",
                "title": "eczane",
                "amount": 251.53
            },
             {
                "type": "gider",
                "category": "alisveris",
                "title": "trendyol",
                "amount": 379.05
            },
            {
                "type": "gider",
                "category": "alisveris",
                "title": "lcw",
                "amount": 1779.97
            },
             {
                "type": "gider",
                "category": "alisveris",
                "title": "mrdiy",
                "amount": 312
            }
        ]
    },
    {
        "date": "2026-07-04",
        "transactions": [
            {
                "type": "gider",
                "category": "alisveris",
                "title": "trendyol",
                "amount": 209.89
            },
             {
                "type": "gider",
                "category": "arac",
                "title": "hgs",
                "amount": 1520
            },
             {
                "type": "gider",
                "category": "alisveris",
                "title": "trendyol",
                "amount": 353.98
            }    
        ]
    },
        {
        "date": "2026-07-05",
        "transactions": [
            {
                "type": "gider",
                "category": "alisveris",
                "title": "trendyol",
                "amount": 208.95
            },
              {
                "type": "gider",
                "category": "market",
                "title": "migros",
                "amount": 453.89
            }
        ]
    },
    {
        "date": "2026-07-06",
        "transactions": [
            {
                "type": "gider",
                "category": "taksit",
                "title": "bisiklet ilk taksit",
                "amount": 2683.89
            },
             {
                "type": "gider",
                "category": "saglik",
                "title": "eczane",
                "amount": 280
            },
             {
                "type": "gider",
                "category": "alisveris",
                "title": "tedi",
                "amount": 989.93
            }
        ]
    },
    {
        "date": "2026-07-09",
        "transactions": [
            {
                "type": "gider",
                "category": "alisveris",
                "title": "amazon",
                "amount": 1280
            },
             {
                "type": "gider",
                "category": "alisveris",
                "title": "trendyol",
                "amount": 679.80
            }
        ]
    },
    {
        "date": "2026-07-10",
        "transactions": [
            {
                "type": "gider",
                "category": "yemek",
                "title": "leyya gelato",
                "amount": 875
            },
             {
                "type": "gider",
                "category": "alisveris",
                "title": "trendyol",
                "amount": 649
            }
        ]
    },
    {
        "date": "2026-07-11",
        "transactions": [
            {
                "type": "gider",
                "category": "taksit",
                "title": "clio zorunlu trafik ilk taksit",
                "amount": 2818.63
            },
             {
                "type": "gider",
                "category": "taksit",
                "title": "clio sigorta ilk taksit",
                "amount": 1430.06
            },
             {
                "type": "gider",
                "category": "alisveris",
                "title": "trendyol",
                "amount": 149
            },
              {
                "type": "gider",
                "category": "alisveris",
                "title": "trendyol",
                "amount": 149.70
            },
             {
                "type": "gider",
                "category": "alisveris",
                "title": "trendyol",
                "amount": 218.50
            }
        ]
    },
    {
        "date": "2026-07-12",
        "transactions": [
            {
                "type": "gider",
                "category": "alisveris",
                "title": "trendyol",
                "amount": 161.10
            },
             {
                "type": "gider",
                "category": "yemek",
                "title": "hamdizade",
                "amount": 1535
            },
              {
                "type": "gider",
                "category": "yemek",
                "title": "trendyol",
                "amount": 1160.07
            },
            {
                "type": "gider",
                "category": "alisveris",
                "title": "google film",
                "amount": 4.99
            }
        ]
    },
    {
        "date": "2026-07-13",
        "transactions": [
            {
                "type": "gider",
                "category": "arac",
                "title": "noter",
                "amount": 1982.90
            },
             {
                "type": "gider",
                "category": "saglik",
                "title": "natura",
                "amount": 1500
            },
            {
                "type": "gider",
                "category": "alisveris",
                "title": "tedi",
                "amount": 153.89
            },
             {
                "type": "gider",
                "category": "alisveris",
                "title": "youtube",
                "amount": 119.99
            }
        ]
    },
    {
        "date": "2026-07-14",
        "transactions": [
            {
                "type": "gider",
                "category": "taksit",
                "title": "skoda zorunlu trafik ilk taksit",
                "amount": 2583.56
            }
        ]
    },
    {
        "date": "2026-07-15",
        "transactions": [
            {
                "type": "gider",
                "category": "taksit",
                "title": "amazon ilk taksit",
                "amount": 930.68
            },
             {
                "type": "gider",
                "category": "alisveris",
                "title": "trendyol",
                "amount": 525
            },
             {
                "type": "gider",
                "category": "alisveris",
                "title": "trendyol",
                "amount": 279
            }
        ]
    },
    {
        "date": "2026-07-16",
        "transactions": [
            {
                "type": "gider",
                "category": "alisveris",
                "title": "hepsiburada",
                "amount": 523.10
            },
             {
                "type": "gider",
                "category": "alisveris",
                "title": "amazon",
                "amount": 499
            },
            {
                "type": "gider",
                "category": "yemek",
                "title": "kadayif",
                "amount": 900
            }
        ]
    }
    
]
